QuickVisualization/__init__.py
QuickVisualization/data_visualization.py
QuickVisualization-0.0.2.dist-info/LICENSE
QuickVisualization-0.0.2.dist-info/METADATA
QuickVisualization-0.0.2.dist-info/WHEEL
QuickVisualization-0.0.2.dist-info/top_level.txt
QuickVisualization-0.0.2.dist-info/RECORD
